ntptimenow.py
ntptimenow-0.4.dist-info/LICENSE
ntptimenow-0.4.dist-info/METADATA
ntptimenow-0.4.dist-info/WHEEL
ntptimenow-0.4.dist-info/top_level.txt
ntptimenow-0.4.dist-info/RECORD
