Metadata-Version: 2.1
Name: ntptimenow
Version: 0.4
Summary: Python NTP Time Now
Home-page: https://github.com/wannaphong/pyntptimenow
Author: Wannaphong Phatthiyaphaibun
Author-email: wannaphong@kkumail.com
License: MIT
Platform: UNKNOWN
Classifier: License :: OSI Approved :: MIT License
Classifier: Programming Language :: Python
Classifier: Operating System :: OS Independent
Classifier: Topic :: System :: Networking :: Time Synchronization
Requires-Dist: ntplib
